.travis.yml
CHANGES.txt
README.rst
bootstrap.py
buildout.cfg
setup.cfg
setup.py
versions.cfg
docs/todo.txt
kotti_paster/__init__.py
kotti_paster/conftest.py
kotti_paster/tests.py
kotti_paster.egg-info/PKG-INFO
kotti_paster.egg-info/SOURCES.txt
kotti_paster.egg-info/dependency_links.txt
kotti_paster.egg-info/entry_points.txt
kotti_paster.egg-info/not-zip-safe
kotti_paster.egg-info/requires.txt
kotti_paster.egg-info/top_level.txt
kotti_paster/paster_templates/__init__.py
kotti_paster/paster_templates/kotti_addon/addon/CHANGES.txt_tmpl
kotti_paster/paster_templates/kotti_addon/addon/README.rst_tmpl
kotti_paster/paster_templates/kotti_addon/addon/development.ini_tmpl
kotti_paster/paster_templates/kotti_addon/addon/setup.cfg_tmpl
kotti_paster/paster_templates/kotti_addon/addon/setup.py_tmpl
kotti_paster/paster_templates/kotti_addon/addon/+package+/__init__.py_tmpl
kotti_paster/paster_templates/kotti_addon/addon/+package+/fanstatic.py_tmpl
kotti_paster/paster_templates/kotti_addon/addon/+package+/static/style.css
kotti_paster/paster_templates/kotti_addon/addon/+package+/tests/conftest.py_tmpl
kotti_paster/paster_templates/kotti_addon/addon/+package+/tests/test_browser_minimal.rst_tmpl
kotti_paster/paster_templates/kotti_addon/addon/+package+/tests/test_example.py
kotti_paster/paster_templates/kotti_addon/contenttype/+package+/__init__.py_tmpl
kotti_paster/paster_templates/kotti_addon/contenttype/+package+/resources.py_tmpl
kotti_paster/paster_templates/kotti_addon/contenttype/+package+/views.py_tmpl
kotti_paster/paster_templates/kotti_addon/contenttype/+package+/templates/view.pt_tmpl
kotti_paster/paster_templates/kotti_addon/contenttype/+package+/tests/test_browser_content_type.rst_tmpl
kotti_paster/paster_templates/kotti_addon/contenttype/+package+/tests/test_functional_content_type.py_tmpl
kotti_paster/paster_templates/kotti_project/buildout/bootstrap.py
kotti_paster/paster_templates/kotti_project/buildout/buildout.cfg_tmpl
kotti_paster/paster_templates/kotti_project/buildout/development.ini_tmpl
kotti_paster/paster_templates/kotti_project/git/+dot+gitignore_tmpl
kotti_paster/paster_templates/kotti_project/travis/+dot+travis.yml
local/.travis.yml
local/CHANGES.txt
local/README.rst
local/bootstrap.py
