Metadata-Version: 1.1
Name: kotti-paster
Version: 0.2
Summary: Paster AddOn Template for Kotti
Home-page: http://pypi.python.org/pypi/kotti_paster/
Author: Marco Scheidhuber and Tom Lazar
Author-email: j23d@jusid.de
License: BSD-derived (http://www.repoze.org/LICENSE.txt)
Keywords: kotti addon scaffold
Platform: UNKNOWN
Classifier: Programming Language :: Python
Classifier: Framework :: Buildout
Classifier: License :: Repoze Public License
